{
  "indexes": [
    {
      "collectionGroup": "clients",
      "queryScope": "COLLECTION",
      "fields": [
        { "fieldPath": "updatedAt", "order": "ASCENDING" },
        { "fieldPath": "name", "order": "ASCENDING" }
      ]
    },
    {
      "collectionGroup": "clients",
      "queryScope": "COLLECTION",
      "fields": [
        { "fieldPath": "updatedAt", "order": "DESCENDING" },
        { "fieldPath": "createdAt", "order": "DESCENDING" }
      ]
    },
    {
      "collectionGroup": "workOrders",
      "queryScope": "COLLECTION",
      "fields": [
        { "fieldPath": "updatedAt", "order": "ASCENDING" },
        { "fieldPath": "status", "order": "ASCENDING" },
        { "fieldPath": "createdAt", "order": "DESCENDING" }
      ]
    },
    {
      "collectionGroup": "workOrders",
      "queryScope": "COLLECTION",
      "fields": [
        { "fieldPath": "clientId", "order": "ASCENDING" },
        { "fieldPath": "createdAt", "order": "DESCENDING" }
      ]
    },
    {
      "collectionGroup": "workOrders",
      "queryScope": "COLLECTION",
      "fields": [
        { "fieldPath": "status", "order": "ASCENDING" },
        { "fieldPath": "priority", "order": "DESCENDING" },
        { "fieldPath": "createdAt", "order": "DESCENDING" }
      ]
    },
    {
      "collectionGroup": "ledger",
      "queryScope": "COLLECTION",
      "fields": [
        { "fieldPath": "updatedAt", "order": "ASCENDING" },
        { "fieldPath": "effectiveDate", "order": "DESCENDING" }
      ]
    },
    {
      "collectionGroup": "ledger",
      "queryScope": "COLLECTION",
      "fields": [
        { "fieldPath": "type", "order": "ASCENDING" },
        { "fieldPath": "effectiveDate", "order": "DESCENDING" }
      ]
    },
    {
      "collectionGroup": "ledger",
      "queryScope": "COLLECTION",
      "fields": [
        { "fieldPath": "category", "order": "ASCENDING" },
        { "fieldPath": "effectiveDate", "order": "DESCENDING" }
      ]
    },
    {
      "collectionGroup": "ledger",
      "queryScope": "COLLECTION",
      "fields": [
        { "fieldPath": "effectiveDate", "order": "ASCENDING" },
        { "fieldPath": "type", "order": "ASCENDING" },
        { "fieldPath": "amount", "order": "DESCENDING" }
      ]
    },
    {
      "collectionGroup": "catalogParts",
      "queryScope": "COLLECTION",
      "fields": [
        { "fieldPath": "updatedAt", "order": "ASCENDING" },
        { "fieldPath": "name", "order": "ASCENDING" }
      ]
    },
    {
      "collectionGroup": "catalogParts",
      "queryScope": "COLLECTION",
      "fields": [
        { "fieldPath": "category", "order": "ASCENDING" },
        { "fieldPath": "name", "order": "ASCENDING" }
      ]
    },
    {
      "collectionGroup": "catalogServices",
      "queryScope": "COLLECTION",
      "fields": [
        { "fieldPath": "updatedAt", "order": "ASCENDING" },
        { "fieldPath": "name", "order": "ASCENDING" }
      ]
    },
    {
      "collectionGroup": "catalogServices",
      "queryScope": "COLLECTION",
      "fields": [
        { "fieldPath": "category", "order": "ASCENDING" },
        { "fieldPath": "name", "order": "ASCENDING" }
      ]
    }
  ],
  "fieldOverrides": [
    {
      "collectionGroup": "workOrders",
      "fieldPath": "tags",
      "indexes": [
        { "order": "ASCENDING", "queryScope": "COLLECTION" },
        { "arrayConfig": "CONTAINS", "queryScope": "COLLECTION" }
      ]
    },
    {
      "collectionGroup": "clients",
      "fieldPath": "tags",
      "indexes": [
        { "arrayConfig": "CONTAINS", "queryScope": "COLLECTION" }
      ]
    }
  ]
}
